{"Game":{"Created":"1732282482870145","FoodSpawns":[],"HazardSpawns":[],"Height":11,"ID":"dcd9755c-76dd-4576-8ee9-7e75dc785ed2","Map":"standard","MaxTurns":7200,"RulesStages":["game_over.standard","movement.standard","starvation.standard","hazard_damage.standard","feed_snakes.standard","elimination.standard"],"Ruleset":{"foodSpawnChance":"15","minimumFood":"1","name":"standard"},"RulesetName":"standard","SnakeTimeout":500,"Source":"ladder","Status":"complete","Width":11},"LastFrame":{"Food":[{"X":5,"Y":5},{"X":4,"Y":7},{"X":5,"Y":1},{"X":2,"Y":2},{"X":0,"Y":2},{"X":6,"Y":1},{"X":9,"Y":7}],"GameState":{},"Hazards":[],"PointState":[],"Snakes":[{"APIVersion":"","Author":"coreyja","Body":[{"X":0,"Y":9},{"X":1,"Y":9},{"X":2,"Y":9},{"X":3,"Y":9},{"X":3,"Y":8},{"X":4,"Y":8},{"X":5,"Y":8},{"X":6,"Y":8},{"X":7,"Y":8},{"X":7,"Y":9},{"X":8,"Y":9},{"X":8,"Y":8}],"Color":"#da8a1a","Death":null,"Error":"","HeadType":"beach-puffin-special","Health":95,"ID":"gs_4q3VR3JMrCPWc8brYPxwYCTd","IsBot":false,"IsEnvironment":false,"Latency":"22","Name":"Hovering Hobbs","ProxyURL":"","Shout":"","Squad":"","StatusCode":200,"TailType":"beach-puffin-special","TimingMicros":{"Connect":1087,"DNS":1007,"FirstByte":90719,"Latency":90796,"TLS":2644},"URL":""},{"APIVersion":"","Author":"Der Informatiker","Body":[{"X":0,"Y":9},{"X":0,"Y":10},{"X":1,"Y":10},{"X":2,"Y":10},{"X":3,"Y":10},{"X":4,"Y":10},{"X":5,"Y":10},{"X":6,"Y":10},{"X":7,"Y":10},{"X":8,"Y":10},{"X":9,"Y":10}],"Color":"#00ffee","Death":{"Cause":"head-collision","EliminatedBy":"gs_4q3VR3JMrCPWc8brYPxwYCTd","Turn":119},"Error":"","HeadType":"smart-caterpillar","Health":88,"ID":"gs_PFwP9w3cMc484ttQDqPdgcBT","IsBot":false,"IsEnvironment":false,"Latency":"264","Name":"Snakeformatika","ProxyURL":"","Shout":"","Squad":"","StatusCode":200,"TailType":"mouse","TimingMicros":{"Connect":1167,"DNS":1170,"FirstByte":434010,"Latency":434093,"TLS":4095},"URL":""}],"Turn":119}}